wheke_sqlite/__init__.py
wheke_sqlite/_cli.py
wheke_sqlite/_pod.py
wheke_sqlite/_service.py
wheke_sqlite/_settings.py
wheke_sqlite/py.typed
wheke_sqlite-0.2.0.dist-info/METADATA
wheke_sqlite-0.2.0.dist-info/WHEEL
wheke_sqlite-0.2.0.dist-info/top_level.txt
wheke_sqlite-0.2.0.dist-info/RECORD
