Metadata-Version: 2.4
Name: wheke-sqlite
Version: 0.2.0
Summary: Add sqlite capabilities to wheke with sqlmodel
Requires-Python: >=3.12
Requires-Dist: sqlmodel
Requires-Dist: wheke
